aliyun/__init__.py
easy_cs_rec_custommodel-0.9.2.dist-info/licenses/LICENSE
easy_rec/__init__.py
easy_rec/version.py
easy_rec/python/__init__.py
easy_rec/python/eval.py
easy_rec/python/export.py
easy_rec/python/main.py
easy_rec/python/predict.py
easy_rec/python/predict_cs.py
easy_rec/python/train_eval.py
easy_rec/python/builders/__init__.py
easy_rec/python/builders/hyperparams_builder.py
easy_rec/python/builders/loss_builder.py
easy_rec/python/builders/optimizer_builder.py
easy_rec/python/builders/strategy_builder.py
easy_rec/python/compat/__init__.py
easy_rec/python/compat/adam_s.py
easy_rec/python/compat/array_ops.py
easy_rec/python/compat/dynamic_variable.py
easy_rec/python/compat/early_stopping.py
easy_rec/python/compat/embedding_ops.py
easy_rec/python/compat/embedding_parallel_saver.py
easy_rec/python/compat/estimator_train.py
easy_rec/python/compat/exporter.py
easy_rec/python/compat/layers.py
easy_rec/python/compat/ops.py
easy_rec/python/compat/optimizers.py
easy_rec/python/compat/queues.py
easy_rec/python/compat/regularizers.py
easy_rec/python/compat/sok_optimizer.py
easy_rec/python/compat/sync_replicas_optimizer.py
easy_rec/python/compat/weight_decay_optimizers.py
easy_rec/python/compat/feature_column/__init__.py
easy_rec/python/compat/feature_column/feature_column.py
easy_rec/python/compat/feature_column/feature_column_v2.py
easy_rec/python/compat/feature_column/sequence_feature_column.py
easy_rec/python/compat/feature_column/utils.py
easy_rec/python/core/__init__.py
easy_rec/python/core/learning_schedules.py
easy_rec/python/core/metrics.py
easy_rec/python/core/sampler.py
easy_rec/python/core/easyrec_metrics/__init__.py
easy_rec/python/core/easyrec_metrics/distribute_metrics_impl_pai.py
easy_rec/python/core/easyrec_metrics/distribute_metrics_impl_tf.py
easy_rec/python/feature_column/__init__.py
easy_rec/python/feature_column/feature_column.py
easy_rec/python/feature_column/feature_group.py
easy_rec/python/hpo/__init__.py
easy_rec/python/hpo/emr_hpo.py
easy_rec/python/hpo/generate_hpo_sql.py
easy_cs_rec_custommodel-0.9.2.dist-info/METADATA
easy_cs_rec_custommodel-0.9.2.dist-info/WHEEL
easy_cs_rec_custommodel-0.9.2.dist-info/top_level.txt
easy_cs_rec_custommodel-0.9.2.dist-info/RECORD
